thorchainpy/__init__.py
thorchainpy/api/__init__.py
thorchainpy/api/borrowers/__init__.py
thorchainpy/api/borrowers/borrower.py
thorchainpy/api/borrowers/borrowers.py
thorchainpy/api/health/__init__.py
thorchainpy/api/health/ping.py
thorchainpy/api/invariants/__init__.py
thorchainpy/api/invariants/invariant.py
thorchainpy/api/invariants/invariants.py
thorchainpy/api/liquidity_providers/__init__.py
thorchainpy/api/liquidity_providers/liquidity_provider.py
thorchainpy/api/liquidity_providers/liquidity_providers.py
thorchainpy/api/mimir/__init__.py
thorchainpy/api/mimir/mimir.py
thorchainpy/api/mimir/mimir_admin.py
thorchainpy/api/mimir/mimir_key.py
thorchainpy/api/mimir/mimir_node.py
thorchainpy/api/mimir/mimir_nodes.py
thorchainpy/api/network/__init__.py
thorchainpy/api/network/ban.py
thorchainpy/api/network/constants.py
thorchainpy/api/network/inbound_addresses.py
thorchainpy/api/network/lastblock.py
thorchainpy/api/network/lastblock_chain.py
thorchainpy/api/network/network.py
thorchainpy/api/network/ragnarok.py
thorchainpy/api/network/version.py
thorchainpy/api/nodes/__init__.py
thorchainpy/api/nodes/node.py
thorchainpy/api/nodes/nodes.py
thorchainpy/api/pol/__init__.py
thorchainpy/api/pol/pol.py
thorchainpy/api/pools/__init__.py
thorchainpy/api/pools/pool.py
thorchainpy/api/pools/pools.py
thorchainpy/api/queue/__init__.py
thorchainpy/api/queue/queue.py
thorchainpy/api/queue/queue_outbound.py
thorchainpy/api/queue/queue_scheduled.py
thorchainpy/api/queue/queue_swap.py
thorchainpy/api/quote/__init__.py
thorchainpy/api/quote/quotesaverdeposit.py
thorchainpy/api/quote/quotesaverwithdraw.py
thorchainpy/api/quote/quoteswap.py
thorchainpy/api/savers/__init__.py
thorchainpy/api/savers/saver.py
thorchainpy/api/savers/savers.py
thorchainpy/api/thornames/__init__.py
thorchainpy/api/thornames/thorname.py
thorchainpy/api/transactions/__init__.py
thorchainpy/api/transactions/tx.py
thorchainpy/api/transactions/tx_signers.py
thorchainpy/api/transactions/tx_signers_old.py
thorchainpy-0.0.2.dist-info/METADATA
thorchainpy-0.0.2.dist-info/WHEEL
thorchainpy-0.0.2.dist-info/RECORD
