Metadata-Version: 2.1
Name: thorchainpy
Version: 0.0.2
Summary: Thorchain Python SDK
License: MIT
Author: sbneo2022
Requires-Python: ==3.11.2
Classifier: License :: OSI Approved :: MIT License
Classifier: Programming Language :: Python :: 3
